atlinter/__init__.py
atlinter/data.py
atlinter/optical_flow.py
atlinter/pair_interpolation.py
atlinter/utils.py
atlinter/version.py
atlinter/metrics/__init__.py
atlinter/metrics/fid.py
atlinter/vendor/__init__.py
atlinter/vendor/MaskFlowNet/__init__.py
atlinter/vendor/MaskFlowNet/logger.py
atlinter/vendor/MaskFlowNet/path.py
atlinter/vendor/MaskFlowNet/predict_new_data.py
atlinter/vendor/MaskFlowNet/network/MaskFlownet.py
atlinter/vendor/MaskFlowNet/network/__init__.py
atlinter/vendor/MaskFlowNet/network/layer.py
atlinter/vendor/MaskFlowNet/network/pipeline.py
atlinter/vendor/MaskFlowNet/network/config/__init__.py
atlinter/vendor/RAFT/__init__.py
atlinter/vendor/RAFT/corr.py
atlinter/vendor/RAFT/datasets.py
atlinter/vendor/RAFT/extractor.py
atlinter/vendor/RAFT/raft.py
atlinter/vendor/RAFT/update.py
atlinter/vendor/RAFT/utils/__init__.py
atlinter/vendor/RAFT/utils/augmentor.py
atlinter/vendor/RAFT/utils/flow_viz.py
atlinter/vendor/RAFT/utils/frame_utils.py
atlinter/vendor/RAFT/utils/utils.py
atlinter/vendor/cain/__init__.py
atlinter/vendor/cain/cain.py
atlinter/vendor/cain/cain_encdec.py
atlinter/vendor/cain/cain_noca.py
atlinter/vendor/cain/common.py
atlinter/vendor/rife/IFNet.py
atlinter/vendor/rife/IFNet15C.py
atlinter/vendor/rife/IFNet2F.py
atlinter/vendor/rife/IFNet2F15C.py
atlinter/vendor/rife/IFNet_HD.py
atlinter/vendor/rife/IFNet_HDv2.py
atlinter/vendor/rife/RIFE.py
atlinter/vendor/rife/RIFE15C.py
atlinter/vendor/rife/RIFE2F.py
atlinter/vendor/rife/RIFE2F15C.py
atlinter/vendor/rife/RIFE_HD.py
atlinter/vendor/rife/RIFE_HDv2.py
atlinter/vendor/rife/__init__.py
atlinter/vendor/rife/loss.py
atlinter/vendor/rife/warplayer.py
atlinter-0.2.3.dist-info/AUTHORS.txt
atlinter-0.2.3.dist-info/LICENSE.txt
atlinter-0.2.3.dist-info/METADATA
atlinter-0.2.3.dist-info/WHEEL
atlinter-0.2.3.dist-info/top_level.txt
atlinter-0.2.3.dist-info/RECORD
