Metadata-Version: 2.1
Name: atlinter
Version: 0.2.3
Summary: Interpolate missing section images in gene expression volumes
Home-page: https://github.com/BlueBrain/atlas-interpolation
Author: Blue Brain Project, EPFL
License: Apache-2.0
Project-URL: Source, https://github.com/BlueBrain/atlas-interpolation
Project-URL: Tracker, https://github.com/BlueBrain/atlas-interpolation/issues
Platform: UNKNOWN
Classifier: License :: OSI Approved :: Apache Software License
Classifier: Operating System :: Unix
Classifier: Operating System :: MacOS
Classifier: Programming Language :: Python :: 3.7
Requires-Python: ~=3.7.0
License-File: LICENSE.txt
License-File: AUTHORS.txt
Requires-Dist: mxnet
Requires-Dist: numpy
Requires-Dist: pytorch-fid
Requires-Dist: pyyaml
Requires-Dist: scipy
Requires-Dist: torch
Requires-Dist: torchvision
Provides-Extra: data
Requires-Dist: atlannot ; extra == 'data'
Requires-Dist: atldld (==0.2.2) ; extra == 'data'
Requires-Dist: dvc[ssh] ; extra == 'data'
Requires-Dist: pillow ; extra == 'data'
Requires-Dist: pynrrd ; extra == 'data'
Requires-Dist: requests ; extra == 'data'
Requires-Dist: scikit-image ; extra == 'data'
Provides-Extra: dev
Requires-Dist: bandit ; extra == 'dev'
Requires-Dist: black ; extra == 'dev'
Requires-Dist: flake8 ; extra == 'dev'
Requires-Dist: flake8-bugbear ; extra == 'dev'
Requires-Dist: flake8-comprehensions ; extra == 'dev'
Requires-Dist: flake8-docstrings ; extra == 'dev'
Requires-Dist: isort ; extra == 'dev'
Requires-Dist: py-vendor (==0.1.2) ; extra == 'dev'
Requires-Dist: pytest ; extra == 'dev'
Requires-Dist: pytest-cov ; extra == 'dev'
Requires-Dist: tox ; extra == 'dev'
Provides-Extra: docs
Requires-Dist: sphinx ; extra == 'docs'
Requires-Dist: sphinx-bluebrain-theme ; extra == 'docs'
Provides-Extra: optical
Requires-Dist: opencv-python ; extra == 'optical'
Requires-Dist: flow-vis ; extra == 'optical'
Requires-Dist: moviepy ; extra == 'optical'
